op_python/__init__.py
op_python/op_client.py
op_python-0.1.0.dist-info/LICENSE
op_python-0.1.0.dist-info/METADATA
op_python-0.1.0.dist-info/WHEEL
op_python-0.1.0.dist-info/RECORD
