Metadata-Version: 2.3
Name: op-python
Version: 0.1.0
Summary: Python wrapper for 1Password CLI (op) for managing secrets
License: MIT
Keywords: 1password,secrets,cli,password-manager
Author: Nathan Eric Norman
Author-email: nenorman@norme.sh
Requires-Python: >=3.9
Classifier: Development Status :: 3 - Alpha
Classifier: Intended Audience :: Developers
Classifier: License :: OSI Approved :: MIT License
Classifier: Programming Language :: Python :: 3
Classifier: Programming Language :: Python :: 3.9
Classifier: Programming Language :: Python :: 3.10
Classifier: Programming Language :: Python :: 3.11
Classifier: Programming Language :: Python :: 3.12
Classifier: Topic :: Security
Classifier: Topic :: Software Development :: Libraries :: Python Modules
Requires-Dist: python-dotenv (>=1.0.0)
Project-URL: Homepage, https://github.com/IvoryNomad/op-python
Project-URL: Issues, https://github.com/IvoryNomad/op-python/issues
Project-URL: Repository, https://github.com/IvoryNomad/op-python
